{
  "description": "TBD",
  "properties": {
    "name": {
      "sequenced": false,
      "singular": false
    },
    "dataType": {
      "sequenced": false,
      "singular": false
    },
    "icon": {
      "sequenced": false,
      "singular": false
    },
    "bundleImage": {
      "sequenced": false,
      "singular": false
    }
  },
  "relations": {
    "importerRun": {
      "sequenced": false,
      "singular": false
    }
  },
  "foregroundColor": "#ffffff",
  "backgroundColor": "#93c47d"
}